rsmtool/__init__.py
rsmtool/analyzer.py
rsmtool/comparer.py
rsmtool/configuration_parser.py
rsmtool/container.py
rsmtool/convert_feature_json.py
rsmtool/fairness_utils.py
rsmtool/modeler.py
rsmtool/preprocessor.py
rsmtool/reader.py
rsmtool/reporter.py
rsmtool/rsmcompare.py
rsmtool/rsmeval.py
rsmtool/rsmexplain.py
rsmtool/rsmpredict.py
rsmtool/rsmsummarize.py
rsmtool/rsmtool.py
rsmtool/rsmxval.py
rsmtool/test_utils.py
rsmtool/transformer.py
rsmtool/version.py
rsmtool/writer.py
rsmtool/notebooks/builtin_model.ipynb
rsmtool/notebooks/consistency.ipynb
rsmtool/notebooks/data_description.ipynb
rsmtool/notebooks/data_description_by_group.ipynb
rsmtool/notebooks/dff_by_group.ipynb
rsmtool/notebooks/evaluation.ipynb
rsmtool/notebooks/evaluation_by_group.ipynb
rsmtool/notebooks/fairness_analyses.ipynb
rsmtool/notebooks/feature_descriptives.ipynb
rsmtool/notebooks/features_by_group.ipynb
rsmtool/notebooks/footer.ipynb
rsmtool/notebooks/header.ipynb
rsmtool/notebooks/intermediate_file_paths.ipynb
rsmtool/notebooks/pca.ipynb
rsmtool/notebooks/preprocessed_features.ipynb
rsmtool/notebooks/skll_model.ipynb
rsmtool/notebooks/sysinfo.ipynb
rsmtool/notebooks/true_score_evaluation.ipynb
rsmtool/notebooks/comparison/consistency.ipynb
rsmtool/notebooks/comparison/evaluation.ipynb
rsmtool/notebooks/comparison/feature_descriptives.ipynb
rsmtool/notebooks/comparison/features_by_group.ipynb
rsmtool/notebooks/comparison/footer.ipynb
rsmtool/notebooks/comparison/header.ipynb
rsmtool/notebooks/comparison/model.ipynb
rsmtool/notebooks/comparison/notes.ipynb
rsmtool/notebooks/comparison/pca.ipynb
rsmtool/notebooks/comparison/preprocessed_features.ipynb
rsmtool/notebooks/comparison/preprocessed_features_by_group.ipynb
rsmtool/notebooks/comparison/score_distributions.ipynb
rsmtool/notebooks/comparison/sysinfo.ipynb
rsmtool/notebooks/comparison/true_score_evaluation.ipynb
rsmtool/notebooks/explanations/auto_cohorts.ipynb
rsmtool/notebooks/explanations/data_description.ipynb
rsmtool-11.3.0.dist-info/LICENSE
rsmtool-11.3.0.dist-info/METADATA
rsmtool-11.3.0.dist-info/WHEEL
rsmtool-11.3.0.dist-info/entry_points.txt
rsmtool-11.3.0.dist-info/top_level.txt
rsmtool-11.3.0.dist-info/RECORD
