Metadata-Version: 2.1
Name: rsmtool
Version: 11.3.0
Summary: Rater scoring modeling tool
Home-page: http://github.com/EducationalTestingService/rsmtool
Maintainer: Nitin Madnani
Maintainer-email: nmadnani@ets.org
License: Apache 2
Keywords: scoring modeling
Classifier: Intended Audience :: Science/Research
Classifier: Intended Audience :: Developers
Classifier: Programming Language :: Python
Classifier: Topic :: Scientific/Engineering
Classifier: Operating System :: Microsoft :: Windows
Classifier: Operating System :: POSIX
Classifier: Operating System :: Unix
Classifier: Operating System :: MacOS
Classifier: Programming Language :: Python :: 3
Classifier: Programming Language :: Python :: 3.8
Classifier: Programming Language :: Python :: 3.9
Classifier: Programming Language :: Python :: 3.10
Classifier: Programming Language :: Python :: 3.11
License-File: LICENSE
Requires-Dist: doc2dash
Requires-Dist: ipython
Requires-Dist: jupyter
Requires-Dist: nose2
Requires-Dist: notebook
Requires-Dist: numpy <2
Requires-Dist: openpyxl
Requires-Dist: pandas
Requires-Dist: pre-commit
Requires-Dist: seaborn
Requires-Dist: shap
Requires-Dist: skll ==4.0.1
Requires-Dist: sphinx
Requires-Dist: sphinx-design
Requires-Dist: sphinx-rtd-theme
Requires-Dist: statsmodels
Requires-Dist: tqdm
Requires-Dist: wandb
Requires-Dist: xlrd
Requires-Dist: xlwt
